LICENSE
MANIFEST.in
README.rst
setup.py
amon/__init__.py
amon/defaults.py
amon.egg-info/PKG-INFO
amon.egg-info/SOURCES.txt
amon.egg-info/dependency_links.txt
amon.egg-info/requires.txt
amon.egg-info/top_level.txt
amon/api/__init__.py
amon/api/exception.py
amon/api/log.py
amon/api/models.py
amon/backends/__init__.py
amon/backends/mongodb.py
amon/core/__init__.py
amon/core/exceptions.py
amon/core/settings.py
amon/system/__init__.py
amon/system/_linux.py
amon/system/_macos.py
amon/system/collector.py
amon/system/daemon.py
amon/system/runner.py
amon/system/utils.py
amon/utils/__init__.py
amon/utils/dates.py
amon/web/__init__.py
amon/web/devserver.py
amon/web/forms.py
amon/web/models.py
amon/web/server.py
amon/web/settings.py
amon/web/template.py
amon/web/utils.py
amon/web/libs/__init__.py
amon/web/libs/jinja2htmlcompress.py
amon/web/libs/session.py
amon/web/media/Gemfile
amon/web/media/Gemfile.lock
amon/web/media/Guardfile
amon/web/media/config.rb
amon/web/media/charts/index.html
amon/web/media/css/chart.css
amon/web/media/css/chosen-sprite.png
amon/web/media/css/chosen.css
amon/web/media/css/error.css
amon/web/media/css/jquery-ui.css
amon/web/media/css/login.css
amon/web/media/css/new_design.css
amon/web/media/css/rickshaw.min.css
amon/web/media/css/screen.css
amon/web/media/css/images/ui-bg_diagonals-thick_18_b81900_40x40.png
amon/web/media/css/images/ui-bg_diagonals-thick_20_666666_40x40.png
amon/web/media/css/images/ui-bg_flat_10_000000_40x100.png
amon/web/media/css/images/ui-bg_highlight-soft_100_eeeeee_1x100.png
amon/web/media/css/images/ui-bg_highlight-soft_75_ffe45c_1x100.png
amon/web/media/css/images/ui-icons_222222_256x240.png
amon/web/media/css/images/ui-icons_228ef1_256x240.png
amon/web/media/css/images/ui-icons_ffffff_256x240.png
amon/web/media/images/active_button.png
amon/web/media/images/arrow-down.png
amon/web/media/images/arrow-up.png
amon/web/media/images/box.png
amon/web/media/images/exception_counter.png
amon/web/media/images/favicon.png
amon/web/media/images/green_bar.png
amon/web/media/images/grey_bar.png
amon/web/media/images/left.png
amon/web/media/images/logo.png
