Metadata-Version: 1.1
Name: amon
Version: 1.0-beta
Summary: Elegant server and web application monitoring toolkit
Home-page: https://github.com/martinrusev/amon
Author: Martin Rusev
Author-email: martinrusev@live.com
License: GPL
Keywords: Amon,monitoring,logging,exception handling
Platform: UNKNOWN
Classifier: Development Status :: 3 - Alpha
Classifier: Environment :: Console
Classifier: Intended Audience :: Developers
Classifier: License :: OSI Approved :: GNU General Public License (GPL)
Classifier: Operating System :: OS Independent
Classifier: Programming Language :: Python
